<?xml version="1.0" encoding="UTF-8"?>
<!DOCTYPE customers SYSTEM "customersOrder.dtd">
<customers>
  <customer id="1">
    <name>John</name>
    <email>john@gmail.com</email>
  </customer>
  <customer id="2">
    <name>Fo Yo</name>
    <email>foyotee@gmail.com</email>
  <ordered><meal><name/><price currency="RM"/><quantity unit="plate"/><totalprice currency="RM">0</totalprice><date>2023-04-08</date></meal></ordered></customer>
  <customer id="3">
    <name>alex</name>
    <email>alex@gmail.com</email>
  </customer>
  <customer id="4">
    <name>junhong</name>
    <email>junhong@gmail.com</email>
  </customer>
  <customer id="5">
    <name>bungseng</name>
    <email>bungseng@gmail.com</email>
  </customer>
</customers>
